quart_flask_patch/__init__.py
quart_flask_patch/_patch.py
quart_flask_patch/_synchronise.py
quart_flask_patch/app.py
quart_flask_patch/cli.py
quart_flask_patch/globals.py
quart_flask_patch/helpers.py
quart_flask_patch/testing.py
quart_flask_patch-0.3.0.dist-info/LICENSE
quart_flask_patch-0.3.0.dist-info/METADATA
quart_flask_patch-0.3.0.dist-info/WHEEL
quart_flask_patch-0.3.0.dist-info/RECORD
